suko/__init__.py
suko-0.6.dist-info/entry_points.txt
suko-0.6.dist-info/LICENSE
suko-0.6.dist-info/WHEEL
suko-0.6.dist-info/METADATA
suko-0.6.dist-info/RECORD
